{
  "version": "2",
  "header": {
    "title": "Business Licenses in Chicago",
    "description": "Business licenses issued by the Department of Business Affairs and Consumer Protection in the City of Chicago from 2002 to the present. January 1, 2006 to present. Data is updated daily.",
    "navigation": [
      {
        "label": "Download",
        "url": "https://data.cityofchicago.org/api/views/r5kz-chrr/rows.csv?accessType=DOWNLOAD&bom=true"
      }
    ]
  },
  "cards": [
    {
      "x": 0,
      "y": 8,
      "width": 12,
      "height": 5,
      "vizwit": {
        "title": "License Description",
        "chartType": "histogram",
        "provider": "socrata",
        "domain": "data.cityofchicago.org",
        "dataset": "xqx5-8hwx",
        "groupBy": "site_number",
        "order":"site_number asc"
      }
    },
    {
      "x": 0,
      "y": 2,
      "width": 12,
      "height": 5,
      "vizwit": {
        "title": "Date Issued",
        "description": "Date the license was issued. The spike in December 2012 refers to the City of Chicago's \"Business First!\" initiative (demo).",
        "chartType": "datetime",
        "provider": "socrata",
        "domain": "data.cityofchicago.org",
        "dataset": "xqx5-8hwx",
        "groupBy": "date_trunc_ym(date_issued)",
        "triggerField": "date_issued"
      }
    },

    {
      "x": 0,
      "y": 11,
      "width": 12,
      "height": 7,
      "vizwit": {
        "title": "Business Licenses",
        "chartType": "table",
        "provider": "socrata",
        "domain": "data.cityofchicago.org",
        "dataset": "xqx5-8hwx"
      }
    }
  ]
}